medmodels/__init__.py
medmodels/_medmodels.cpython-313-aarch64-linux-musl.so
medmodels/_medmodels.pyi
medmodels/medrecord/__init__.py
medmodels/medrecord/builder.py
medmodels/medrecord/datatype.py
medmodels/medrecord/indexers.py
medmodels/medrecord/medrecord.py
medmodels/medrecord/overview.py
medmodels/medrecord/querying.py
medmodels/medrecord/schema.py
medmodels/medrecord/types.py
medmodels/py.typed
medmodels/treatment_effect/__init__.py
medmodels/treatment_effect/builder.py
medmodels/treatment_effect/continuous_estimators.py
medmodels/treatment_effect/estimate.py
medmodels/treatment_effect/matching/__init__.py
medmodels/treatment_effect/matching/algorithms/__init__.py
medmodels/treatment_effect/matching/algorithms/classic_distance_models.py
medmodels/treatment_effect/matching/algorithms/propensity_score.py
medmodels/treatment_effect/matching/covariates/__init__.py
medmodels/treatment_effect/matching/covariates/metrics.py
medmodels/treatment_effect/matching/matching.py
medmodels/treatment_effect/matching/neighbors.py
medmodels/treatment_effect/matching/propensity.py
medmodels/treatment_effect/report.py
medmodels/treatment_effect/temporal_analysis.py
medmodels/treatment_effect/treatment_effect.py
medmodels-0.4.9.dist-info/METADATA
medmodels-0.4.9.dist-info/WHEEL
medmodels-0.4.9.dist-info/licenses/LICENSE
medmodels.libs/libgcc_s-9d28dc04.so.1
medmodels-0.4.9.dist-info/RECORD
