Metadata-Version: 2.4
Name: medmodels
Version: 0.4.9
Classifier: Development Status :: 3 - Alpha
Classifier: Intended Audience :: Developers
Classifier: Intended Audience :: Healthcare Industry
Classifier: Intended Audience :: Science/Research
Classifier: License :: OSI Approved :: BSD License
Classifier: Operating System :: MacOS :: MacOS X
Classifier: Operating System :: Microsoft :: Windows
Classifier: Operating System :: POSIX
Classifier: Operating System :: Unix
Classifier: Programming Language :: Python
Classifier: Programming Language :: Python :: 3
Classifier: Programming Language :: Python :: 3.10
Classifier: Programming Language :: Python :: 3.11
Classifier: Programming Language :: Python :: 3.12
Classifier: Programming Language :: Python :: 3.13
Classifier: Programming Language :: Python :: 3 :: Only
Classifier: Programming Language :: Rust
Classifier: Topic :: Scientific/Engineering
Classifier: Topic :: Software Development
Classifier: Typing :: Typed
Requires-Dist: numpy>=2.0.0
Requires-Dist: pandas>=2.2.2
Requires-Dist: polars[pandas]>=1.6.0
Requires-Dist: scikit-learn>=1.5.0
Requires-Dist: scipy>=1.6.1
License-File: LICENSE
Summary: Limebit Medmodels Package
Requires-Python: >=3.10
